capricorn_ai/__init__.py
capricorn_ai/labels.py
capricorn_ai/models.py
capricorn_ai/utils.py
capricorn_ai/ai_models/Capricorn0.1.keras
capricorn_ai/ai_models/__init__.py
capricorn_ai-0.1.1.dist-info/METADATA
capricorn_ai-0.1.1.dist-info/WHEEL
capricorn_ai-0.1.1.dist-info/top_level.txt
capricorn_ai-0.1.1.dist-info/RECORD
