Metadata-Version: 2.4
Name: capricorn-ai
Version: 0.1.1
Summary: Deep learning histopathology classification with Keras
Author: Moshe Newman
License: MIT
Project-URL: Homepage, https://github.com/SigMoses/Capricorn
Project-URL: Repository, https://github.com/SigMoses/Capricorn
Classifier: Programming Language :: Python :: 3
Classifier: Topic :: Scientific/Engineering :: Artificial Intelligence
Classifier: Topic :: Scientific/Engineering :: Image Recognition
Classifier: Intended Audience :: Science/Research
Classifier: License :: OSI Approved :: MIT License
Classifier: Operating System :: OS Independent
Requires-Python: >=3.7
Requires-Dist: numpy>=1.19
Requires-Dist: Pillow>=8.0
Provides-Extra: tensorflow
Requires-Dist: tensorflow>=2.0; extra == "tensorflow"
Provides-Extra: tf-nightly
Requires-Dist: tf-nightly>=2.0; extra == "tf-nightly"
